{
    "flags": {
        "uploadLloydGeorgeWorkflowEnabled": {
            "name": "uploadLloydGeorgeWorkflowEnabled"
        },
        "uploadLambdaEnabled": {
            "name": "uploadLambdaEnabled"
        },
        "uploadArfWorkflowEnabled": {
            "name": "uploadArfWorkflowEnabled"
        },
        "useSmartcardAuth": {
            "name": "useSmartcardAuth"
        },
        "lloydGeorgeValidationStrictModeEnabled": {
            "name": "lloydGeorgeValidationStrictModeEnabled"
        },
        "uploadDocumentIteration3Enabled": {
            "name": "uploadDocumentIteration3Enabled"
        }
    },
    "values": {
        "uploadLloydGeorgeWorkflowEnabled": {
            "enabled": "true"
        },
        "uploadLambdaEnabled": {
            "enabled": "true"
        },
        "uploadArfWorkflowEnabled": {
            "enabled": "true"
        },
        "useSmartcardAuth": {
            "enabled": "false"
        },
        "lloydGeorgeValidationStrictModeEnabled": {
            "enabled": "true"
        },
        "uploadDocumentIteration3Enabled": {
            "enabled": "true"
        }
    },
    "version": "1"
}
